mcp_gsuite/__init__.py
mcp_gsuite/calendar.py
mcp_gsuite/gauth.py
mcp_gsuite/gmail.py
mcp_gsuite/server.py
mcp_gsuite/toolhandler.py
mcp_gsuite/tools_calendar.py
mcp_gsuite/tools_gmail.py
iflow_mcp_mcp_gsuite-0.4.1.dist-info/METADATA
iflow_mcp_mcp_gsuite-0.4.1.dist-info/WHEEL
iflow_mcp_mcp_gsuite-0.4.1.dist-info/entry_points.txt
iflow_mcp_mcp_gsuite-0.4.1.dist-info/licenses/LICENSE
iflow_mcp_mcp_gsuite-0.4.1.dist-info/RECORD
